miso_tool/__about__.py
miso_tool/__init__.py
miso_tool/cleaning.py
miso_tool/cli.py
miso_tool/illumina.py
miso_tool/io.py
miso_tool/main.py
miso_tool/nanopore.py
miso_tool/samples.py
miso_tool/seqruns.py
miso_tool/util.py
miso_tool/barcodes/__init__.py
miso_tool/barcodes/nanopore.py
miso_tool/const/__init__.py
miso_tool/const/organisms.py
miso_tool-0.0.7.dist-info/METADATA
miso_tool-0.0.7.dist-info/WHEEL
miso_tool-0.0.7.dist-info/entry_points.txt
miso_tool-0.0.7.dist-info/licenses/LICENSE.txt
miso_tool-0.0.7.dist-info/RECORD
