Metadata-Version: 2.3
Name: miso-tool
Version: 0.0.7
Summary: A tool to work with sequencing run and sample info from MISO LIMS Pinery JSON data
Project-URL: Documentation, https://github.com/unknown/miso-tool#readme
Project-URL: Issues, https://github.com/unknown/miso-tool/issues
Project-URL: Source, https://github.com/unknown/miso-tool
Author-email: Peter Kruczkiewicz <peter.kruczkiewicz@gmail.com>
License-Expression: Apache-2.0
License-File: LICENSE.txt
Classifier: Development Status :: 4 - Beta
Classifier: Programming Language :: Python
Classifier: Programming Language :: Python :: 3.8
Classifier: Programming Language :: Python :: 3.9
Classifier: Programming Language :: Python :: 3.10
Classifier: Programming Language :: Python :: 3.11
Classifier: Programming Language :: Python :: Implementation :: CPython
Requires-Python: >=3.8
Requires-Dist: pandas
Requires-Dist: pendulum
Requires-Dist: rich
Requires-Dist: tqdm
Requires-Dist: typer
